sentry_fogbugz/models.py
sentry_fogbugz/plugin.py
sentry_fogbugz/__init__.py
sentry_fogbugz-0.1.0.dist-info/DESCRIPTION.rst
sentry_fogbugz-0.1.0.dist-info/RECORD
sentry_fogbugz-0.1.0.dist-info/METADATA
sentry_fogbugz-0.1.0.dist-info/top_level.txt
sentry_fogbugz-0.1.0.dist-info/metadata.json
sentry_fogbugz-0.1.0.dist-info/entry_points.txt
sentry_fogbugz-0.1.0.dist-info/WHEEL
