Metadata-Version: 2.0
Name: sentry-fogbugz
Version: 0.1.0
Summary: A Sentry extension which integrates with Fogbugz
Home-page: https://github.com/glasslion/sentry-fogbugz
Author: Leonardo Zhou
Author-email: glasslion@gmail.com
License: MIT
Keywords: sentry fogbugz
Platform: UNKNOWN
Classifier: Development Status :: 3 - Alpha
Classifier: Intended Audience :: Developers
Classifier: Topic :: Software Development :: Build Tools
Classifier: License :: OSI Approved :: MIT License
Classifier: Programming Language :: Python :: 2
Classifier: Programming Language :: Python :: 2.6
Classifier: Programming Language :: Python :: 2.7
Classifier: Programming Language :: Python :: 3
Classifier: Programming Language :: Python :: 3.3
Classifier: Programming Language :: Python :: 3.4
